Metadata-Version: 2.1
Name: odoo13-addon-stock-dynamic-routing-reserve-rule
Version: 13.0.1.0.1
Summary: Glue module between dynamic routing and reservation rules
Home-page: https://github.com/OCA/wms
Author: Camptocamp, Odoo Community Association (OCA)
Author-email: support@odoo-community.org
License: AGPL-3
Platform: UNKNOWN
Classifier: Programming Language :: Python
Classifier: Framework :: Odoo
Classifier: License :: OSI Approved :: GNU Affero General Public License v3
Classifier: Development Status :: 4 - Beta
Requires-Python: >=3.5
Requires-Dist: odoo13-addon-stock-dynamic-routing
Requires-Dist: odoo13-addon-stock-reserve-rule
Requires-Dist: odoo (<13.1dev,>=13.0a)
